MANIFEST.in
README.md
requirements.txt
setup.py
bdgenomics/__init__.py
bdgenomics.mango.pileup.egg-info/PKG-INFO
bdgenomics.mango.pileup.egg-info/SOURCES.txt
bdgenomics.mango.pileup.egg-info/dependency_links.txt
bdgenomics.mango.pileup.egg-info/not-zip-safe
bdgenomics.mango.pileup.egg-info/requires.txt
bdgenomics.mango.pileup.egg-info/top_level.txt
bdgenomics/mango/__init__.py
bdgenomics/mango/pileup/__init__.py
bdgenomics/mango/pileup/_version.py
bdgenomics/mango/pileup/features.py
bdgenomics/mango/pileup/reads.py
bdgenomics/mango/pileup/variants.py
bdgenomics/mango/pileup/static/extension.js
bdgenomics/mango/pileup/static/index.js
bdgenomics/mango/pileup/static/index.js.map